Fsdb-1.2.2.dist-info/DESCRIPTION.rst
Fsdb-1.2.2.dist-info/METADATA
Fsdb-1.2.2.dist-info/RECORD
Fsdb-1.2.2.dist-info/WHEEL
Fsdb-1.2.2.dist-info/metadata.json
Fsdb-1.2.2.dist-info/top_level.txt
fsdb/__init__.py
fsdb/compat.py
fsdb/config.py
fsdb/fsdb.py
fsdb/hashtools.py
fsdb/utils.py
