Metadata-Version: 2.0
Name: Fsdb
Version: 1.2.2
Summary: File system database. Easily manage file storing
Home-page: https://github.com/ael-code/pyFsdb
Author: Ael
Author-email: tommy.ael@gmail.com
License: LGPLv3
Keywords: database file storing db
Platform: UNKNOWN
Classifier: Development Status :: 5 - Production/Stable
Classifier: License :: OSI Approved :: GNU Lesser General Public License v3 (LGPLv3)
Classifier: Topic :: Database
Classifier: Operating System :: OS Independent
Classifier: Programming Language :: Python :: 2
Classifier: Programming Language :: Python :: 2.6
Classifier: Programming Language :: Python :: 2.7
Classifier: Programming Language :: Python :: 3
Classifier: Programming Language :: Python :: 3.3
Classifier: Programming Language :: Python :: 3.4
Classifier: Programming Language :: Python :: 3.5
